pyzyj/__init__.py
pyzyj/cal_tgt_size_heatmap.py
pyzyj/check_file_difference.py
pyzyj/count_by_class.py
pyzyj/data_frame.py
pyzyj/download.py
pyzyj/evaluate.py
pyzyj/format.py
pyzyj/logger.py
pyzyj/select_tools.py
pyzyj/tiny_copy.py
pyzyj/train_val_divide.py
pyzyj/visualize.py
pyzyj/shutup/__init__.py
pyzyj/shutup/shutup/__init__.py
pyzyj/shutup/tests/__init__.py
pyzyj/shutup/tests/test_shutup.py
pyzyj/torch_utils/__init__.py
pyzyj/torch_utils/utils.py
pyzyj/torchutils/__init__.py
pyzyj/torchutils/model_size.py
pyzyj/yolo_evaluator/__init__.py
pyzyj/yolo_evaluator/evaluator.py
pyzyj/yolo_evaluator/val.py
pyzyj/yolo_evaluator/ultralytics/__init__.py
pyzyj/yolo_evaluator/ultralytics/cfg/__init__.py
pyzyj/yolo_evaluator/ultralytics/data/__init__.py
pyzyj/yolo_evaluator/ultralytics/data/annotator.py
pyzyj/yolo_evaluator/ultralytics/data/augment.py
pyzyj/yolo_evaluator/ultralytics/data/base.py
pyzyj/yolo_evaluator/ultralytics/data/build.py
pyzyj/yolo_evaluator/ultralytics/data/converter.py
pyzyj/yolo_evaluator/ultralytics/data/dataset.py
pyzyj/yolo_evaluator/ultralytics/data/loaders.py
pyzyj/yolo_evaluator/ultralytics/data/split_dota.py
pyzyj/yolo_evaluator/ultralytics/data/utils.py
pyzyj/yolo_evaluator/ultralytics/data/explorer/__init__.py
pyzyj/yolo_evaluator/ultralytics/data/explorer/explorer.py
pyzyj/yolo_evaluator/ultralytics/data/explorer/utils.py
pyzyj/yolo_evaluator/ultralytics/data/explorer/gui/__init__.py
pyzyj/yolo_evaluator/ultralytics/data/explorer/gui/dash.py
pyzyj/yolo_evaluator/ultralytics/engine/__init__.py
pyzyj/yolo_evaluator/ultralytics/engine/exporter.py
pyzyj/yolo_evaluator/ultralytics/engine/model.py
pyzyj/yolo_evaluator/ultralytics/engine/predictor.py
pyzyj/yolo_evaluator/ultralytics/engine/results.py
pyzyj/yolo_evaluator/ultralytics/engine/trainer.py
pyzyj/yolo_evaluator/ultralytics/engine/tuner.py
pyzyj/yolo_evaluator/ultralytics/engine/validator.py
pyzyj/yolo_evaluator/ultralytics/hub/__init__.py
pyzyj/yolo_evaluator/ultralytics/hub/auth.py
pyzyj-1.1.9.dist-info/licenses/LICENSE
pyzyj-1.1.9.dist-info/METADATA
pyzyj-1.1.9.dist-info/WHEEL
pyzyj-1.1.9.dist-info/top_level.txt
pyzyj-1.1.9.dist-info/RECORD
