Metadata-Version: 2.4
Name: pyzyj
Version: 1.1.9
Home-page: https://github.com/ZYJIQVV/pyzyj
Author: zyj
Author-email: 
License: MIT
License-File: LICENSE
Requires-Dist: opencv-python
Requires-Dist: numpy
Requires-Dist: Pillow
Requires-Dist: pycocotools
Requires-Dist: lxml
Requires-Dist: tqdm
Requires-Dist: matplotlib
Requires-Dist: scikit-image
Requires-Dist: scikit-learn
Requires-Dist: pandas
Requires-Dist: pyyaml
Dynamic: author
Dynamic: description
Dynamic: description-content-type
Dynamic: home-page
Dynamic: license
Dynamic: license-file
Dynamic: requires-dist
